cardquant/Figgie.py
cardquant/IMC.py
cardquant/__init__.py
cardquant-0.1.10.dist-info/LICENSE
cardquant-0.1.10.dist-info/METADATA
cardquant-0.1.10.dist-info/WHEEL
cardquant-0.1.10.dist-info/top_level.txt
cardquant-0.1.10.dist-info/RECORD
