Metadata-Version: 2.1
Name: cardquant
Version: 0.1.10
Summary: A library for mock quantitative trading exercises.
Home-page: https://github.com/evansemet/cardquant
Author: Evan Semet
Author-email: evancsemet@gmail.com
License: MIT
Project-URL: Bug Tracker, https://github.com/evansemet/cardquant/issues
Project-URL: Documentation, https://github.com/evansemet/cardquant#readme
Keywords: quantitative trading,options pricing,card games,finance,simulation
Classifier: Programming Language :: Python :: 3
Classifier: License :: OSI Approved :: MIT License
Classifier: Operating System :: OS Independent
Requires-Python: >=3.7
License-File: LICENSE
Requires-Dist: numpy
Requires-Dist: pandas
Requires-Dist: typing_extensions; python_version < "3.9"
